Metadata-Version: 1.1
Name: BasicPyMath
Version: 0.0.1
Summary: Basic Math Library
Home-page: UNKNOWN
Author: Gabriele Ambrogio
Author-email: UNKNOWN
License: MIT
Keywords: math
Platform: UNKNOWN
Classifier: Development Status :: 5 - Production/Stable
Classifier: Intended Audience :: Education
Classifier: Operating System :: Microsoft :: Windows :: Windows 10
Classifier: License :: OSI Approved :: MIT License
Classifier: Programming Language :: Python :: 3
